setup.py
pytotp/__init__.py
pytotp.egg-info/PKG-INFO
pytotp.egg-info/SOURCES.txt
pytotp.egg-info/dependency_links.txt
pytotp.egg-info/top_level.txt