Metadata-Version: 1.1
Name: pytotp
Version: 3
Summary: one time password (totp) for python. c2fa
Home-page: https://github.com/cevin/pytotp
Author: cevin
Author-email: cevin.cheung@gmail.com
License: BSD License
Platform: all
Classifier: Development Status :: 4 - Beta
Classifier: Operating System :: OS Independent
Classifier: Intended Audience :: Developers
Classifier: License :: OSI Approved :: BSD License
Classifier: Programming Language :: Python
Classifier: Programming Language :: Python :: Implementation
Classifier: Programming Language :: Python :: 3
Classifier: Programming Language :: Python :: 3.4
Classifier: Programming Language :: Python :: 3.5
Classifier: Programming Language :: Python :: 3.6
Classifier: Topic :: Software Development :: Libraries
